mcc_api/__init__.py
mcc_api/event/__init__.py
mcc_api/event/enums.py
mcc_api/event/exceptions.py
mcc_api/event/responses.py
mcc_api/island/__init__.py
mcc_api/island/auth.py
mcc_api/island/directives.py
mcc_api/island/enums.py
mcc_api/island/interfaces.py
mcc_api/island/scalars.py
mcc_api/island/types.py
mcc_api-1.4.3.dist-info/METADATA
mcc_api-1.4.3.dist-info/WHEEL
mcc_api-1.4.3.dist-info/licenses/LICENSE
mcc_api-1.4.3.dist-info/RECORD
