Metadata-Version: 2.4
Name: mcc-api
Version: 1.4.3
Summary: Wrapper for the MC Championship APIs (Event and Island)
Project-URL: Repository, https://github.com/JamesMCo/python_mcc_api
Project-URL: Issues, https://github.com/JamesMCo/python_mcc_api/issues
Project-URL: Documentation, https://mrjamesco.uk/python_mcc_api
Author-email: "James C." <james@cordon.click>
License-File: LICENSE
Classifier: License :: OSI Approved :: MIT License
Classifier: Operating System :: OS Independent
Classifier: Programming Language :: Python :: 3
Requires-Python: >=3.10
Requires-Dist: gql[requests]
Requires-Dist: ratelimit
Requires-Dist: requests
